dash_maplibre/Colorbar.py
dash_maplibre/DashMaplibre.py
dash_maplibre/__init__.py
dash_maplibre/_imports_.py
dash_maplibre/dash_maplibre.min.js
dash_maplibre/dash_maplibre.min.js.map
dash_maplibre/metadata.json
dash_maplibre/package-info.json
dash_maplibre-0.0.20.dist-info/licenses/LICENSE
dash_maplibre-0.0.20.dist-info/METADATA
dash_maplibre-0.0.20.dist-info/WHEEL
dash_maplibre-0.0.20.dist-info/top_level.txt
dash_maplibre-0.0.20.dist-info/RECORD
