Metadata-Version: 2.4
Name: dash_maplibre
Version: 0.0.20
Summary: A project for a custom dash component exposing maplibre
Author: Paul-Remo Wagner <wagner@matrisk.com>
License: MIT
Classifier: Framework :: Dash
License-File: LICENSE
Dynamic: author
Dynamic: classifier
Dynamic: description
Dynamic: description-content-type
Dynamic: license
Dynamic: license-file
Dynamic: summary
